 [
    {
      "created_at": "2021-05-11T06:12:10.58131+00:00",
      "email": "abhishek.patil@joflee.com",
      "first_name": "Abhishek",
      "id": "05ee6212-deec-436e-9995-f027e9ad6df5",
      "last_name": "Patil",
      "updated_at": "2021-05-11T06:12:10.58131+00:00"
    },
    {
      "created_at": "2021-05-12T13:00:08.974703+00:00",
      "email": "alangthorn6d@usnews.com",
      "first_name": "Adaline",
      "id": "85779b73-8fac-410e-bccf-42a8377dbc56",
      "last_name": "Langthorn",
      "updated_at": "2021-05-12T13:00:08.974703+00:00"
    },
    {
      "created_at": "2021-05-12T13:00:08.974703+00:00",
      "email": "amarjoribanks5z@adobe.com",
      "first_name": "Adham",
      "id": "468fb4e2-f559-4456-9bb8-34886ad634af",
      "last_name": "Marjoribanks",
      "updated_at": "2021-05-12T13:00:08.974703+00:00"
    },
    {
      "created_at": "2021-05-12T13:00:08.974703+00:00",
      "email": "amactrustam2w@vimeo.com",
      "first_name": "Adlai",
      "id": "3ebef0a3-0b93-41c1-a449-b988677c298e",
      "last_name": "MacTrustam",
      "updated_at": "2021-05-12T13:00:08.974703+00:00"
    },
    {
      "created_at": "2021-05-12T13:00:08.974703+00:00",
      "email": "areinger80@disqus.com",
      "first_name": "Adora",
      "id": "afd5e3e3-0fca-4734-af76-9dc466ae5d8c",
      "last_name": "Reinger",
      "updated_at": "2021-05-12T13:00:08.974703+00:00"
    },
    {
      "created_at": "2021-05-12T13:00:08.974703+00:00",
      "email": "atomini24@woothemes.com",
      "first_name": "Agnese",
      "id": "ccd4b9c0-f2cc-4bee-8a7e-e92facbb5778",
      "last_name": "Tomini",
      "updated_at": "2021-05-12T13:00:08.974703+00:00"
    },
    {
      "created_at": "2021-05-12T13:00:08.974703+00:00",
      "email": "abroy6h@addthis.com",
      "first_name": "Alard",
      "id": "ac8011d5-6b95-43c3-ae0e-133c99f4fd8e",
      "last_name": "Broy",
      "updated_at": "2021-05-12T13:00:08.974703+00:00"
    },
    {
      "created_at": "2021-05-12T13:00:08.974703+00:00",
      "email": "adur1s@facebook.com",
      "first_name": "Alberto",
      "id": "01c18f3e-8431-4157-87cd-36aed8603f4c",
      "last_name": "Dur",
      "updated_at": "2021-05-12T13:00:08.974703+00:00"
    },
    {
      "created_at": "2021-05-12T13:00:08.974703+00:00",
      "email": "ahurt21@timesonline.co.uk",
      "first_name": "Aleksandr",
      "id": "3ee315a1-d0bd-44fa-9afb-f849c6df48ee",
      "last_name": "Hurt",
      "updated_at": "2021-05-12T13:00:08.974703+00:00"
    },
    {
      "created_at": "2021-05-12T13:00:08.974703+00:00",
      "email": "ahuggin7v@hc360.com",
      "first_name": "Alvin",
      "id": "ccc7d4b7-da6b-4518-af2e-2b8b34e73715",
      "last_name": "Huggin",
      "updated_at": "2021-05-12T13:00:08.974703+00:00"
    }
  ]
